[
    {"question_id": 1, "question_content": "Wat is je favoriete boek en waarom?"},
    {"question_id": 2, "question_content": "Beschrijf een gedenkwaardige gebeurtenis uit je leven."},
    {"question_id": 3, "question_content": "Wat zijn je hobby's?"},
    {"question_id": 4, "question_content": "Hoe breng je meestal je weekenden door?"},
    {"question_id": 5, "question_content": "Wat zijn je carrièredoelen?"},
    {"question_id": 6, "question_content": "Kun je uitleggen hoe je jouw favoriete gerecht bereidt?"},
    {"question_id": 7, "question_content": "Wat doe je meestal als je gestrest bent?"},
    {"question_id": 8, "question_content": "Wie is jouw rolmodel en waarom?"},
    {"question_id": 9, "question_content": "Kun je je geboorteplaats beschrijven?"},
    {"question_id": 10, "question_content": "Wat is je favoriete muziekgenre?"},
    {"question_id": 11, "question_content": "Wat doe je meestal tijdens vakanties?"},
    {"question_id": 12, "question_content": "Wat motiveert je om hard te werken?"},
    {"question_id": 13, "question_content": "Kun je je dagelijkse routine beschrijven?"},
    {"question_id": 14, "question_content": "Wat is je droomvakantiebestemming?"},
    {"question_id": 15, "question_content": "Hoe vier je meestal je verjaardag?"},
    {"question_id": 16, "question_content": "Wat is je favoriete film?"},
    {"question_id": 17, "question_content": "Beschrijf een moeilijke situatie die je hebt overwonnen en hoe je dat deed."},
    {"question_id": 18, "question_content": "Wat was je favoriete vak op school of universiteit?"},
    {"question_id": 19, "question_content": "Wat doe je meestal als je nieuwe mensen ontmoet?"},
    {"question_id": 20, "question_content": "Welke eigenschappen zijn het belangrijkst in een vriendschap?"},
    {"question_id": 21, "question_content": "Kun je een vaardigheid beschrijven die je recent hebt geleerd?"},
    {"question_id": 22, "question_content": "Wat is je favoriete sport?"},
    {"question_id": 23, "question_content": "Hoe bereid je je voor op een belangrijke vergadering of examen?"},
    {"question_id": 24, "question_content": "Wat vind je van klimaatverandering?"},
    {"question_id": 25, "question_content": "Wat is de interessantste plaats die je hebt bezocht?"},
    {"question_id": 26, "question_content": "Wat is je favoriete soort eten?"},
    {"question_id": 27, "question_content": "Kun je je droombaan beschrijven?"},
    {"question_id": 28, "question_content": "Wat is het beste advies dat je ooit hebt gekregen?"},
    {"question_id": 29, "question_content": "Wat zijn je toekomstplannen?"},
    {"question_id": 30, "question_content": "Hoe vier je meestal nationale feestdagen?"},
    {"question_id": 31, "question_content": "Wat is je favoriete seizoen en waarom?"},
    {"question_id": 32, "question_content": "Kun je de tradities van je familie beschrijven?"},
    {"question_id": 33, "question_content": "Wat is je favoriete app of website?"},
    {"question_id": 34, "question_content": "Wat is de belangrijkste les die je in het leven hebt geleerd?"},
    {"question_id": 35, "question_content": "Hoe breng je tijd door met je vrienden?"},
    {"question_id": 36, "question_content": "Wat is je favoriete weertype?"},
    {"question_id": 37, "question_content": "Wat vind je van sociale media?"},
    {"question_id": 38, "question_content": "Kun je je beste vriend of vriendin beschrijven?"},
    {"question_id": 39, "question_content": "Wat doe je om gezond te blijven?"},
    {"question_id": 40, "question_content": "Wat zijn de belangrijkste verschillen tussen je moedertaal en het Nederlands?"},
    {"question_id": 41, "question_content": "Wat doe je meestal in je vrije tijd?"},
    {"question_id": 42, "question_content": "Kun je je favoriete jeugdherinnering beschrijven?"},
    {"question_id": 43, "question_content": "Wat is je favoriete traditie tijdens feestdagen?"},
    {"question_id": 44, "question_content": "Wat vind je van reizen?"},
    {"question_id": 45, "question_content": "Kun je iemand beschrijven die jou inspireert?"},
    {"question_id": 46, "question_content": "Wat is volgens jou de beste manier om een nieuwe taal te leren?"},
    {"question_id": 47, "question_content": "Wat is je favoriete kunstvorm?"},
    {"question_id": 48, "question_content": "Wat is je favoriete manier om te ontspannen?"},
    {"question_id": 49, "question_content": "Wat doe je om productief te blijven?"},
    {"question_id": 50, "question_content": "Welke vaardigheden zijn belangrijk voor een succesvolle carrière?"},
    {"question_id": 51, "question_content": "Kun je je favoriete leraar of lerares beschrijven?"},
    {"question_id": 52, "question_content": "Hoe vier je je prestaties?"},
    {"question_id": 53, "question_content": "Wat is je favoriete herinnering met je familie?"},
    {"question_id": 54, "question_content": "Wat is je favoriete citaat en waarom?"},
    {"question_id": 55, "question_content": "Kun je een situatie beschrijven waarin je iemand hebt geholpen?"},
    {"question_id": 56, "question_content": "Wat is je favoriete buitenactiviteit?"},
    {"question_id": 57, "question_content": "Wat zijn de voordelen en nadelen van teamwerk?"},
    {"question_id": 58, "question_content": "Wat vind je van onderwijs?"},
    {"question_id": 59, "question_content": "Wat is het beste cadeau dat je ooit hebt gekregen?"},
    {"question_id": 60, "question_content": "Wat doe je meestal in de winter?"},
    {"question_id": 61, "question_content": "Wat vind je van technologie?"},
    {"question_id": 62, "question_content": "Wat doe je meestal in de zomer?"},
    {"question_id": 63, "question_content": "Kun je je favoriete vakantiebestemming beschrijven?"},
    {"question_id": 64, "question_content": "Wat vind je van het leren van nieuwe vaardigheden?"},
    {"question_id": 65, "question_content": "Wat zijn de voordelen van vrijwilligerswerk?"},
    {"question_id": 66, "question_content": "Wat is je favoriete literaire genre?"},
    {"question_id": 67, "question_content": "Hoe vier je meestal je verjaardag?"},
    {"question_id": 68, "question_content": "Hoe breng je tijd door met je familie?"},
    {"question_id": 69, "question_content": "Kun je een typische dag uit je leven beschrijven?"},
    {"question_id": 70, "question_content": "Wat zijn je favoriete studiemethoden?"},
    {"question_id": 71, "question_content": "Wat vind je van samenwerken in een team?"},
    {"question_id": 72, "question_content": "Wat is je mening over online leren?"},
    {"question_id": 73, "question_content": "Kun je je droomhuis beschrijven?"},
    {"question_id": 74, "question_content": "Wat is je favoriete familie traditie?"},
    {"question_id": 75, "question_content": "Wat zijn de voordelen van het lezen van boeken?"},
    {"question_id": 76, "question_content": "Wat vind je van sport?"},
    {"question_id": 77, "question_content": "Wat is de meest waardevolle les die je hebt geleerd?"},
    {"question_id": 78, "question_content": "Wat vind je van de opwarming van de aarde?"},
    {"question_id": 79, "question_content": "Wat is je favoriete vorm van entertainment?"},
    {"question_id": 80, "question_content": "Kun je een situatie beschrijven waarin je creatief een probleem hebt opgelost?"},
    {"question_id": 81, "question_content": "Wat vind je van een balans tussen werk en privéleven?"},
    {"question_id": 82, "question_content": "Wat doe je meestal in de lente?"},
    {"question_id": 83, "question_content": "Wat is je favoriete herinnering met je vrienden?"},
    {"question_id": 84, "question_content": "Kun je je ideale weekend beschrijven?"},
    {"question_id": 85, "question_content": "Wat is je favoriete manier van reizen?"},
    {"question_id": 86, "question_content": "Wat vind je van culturele verschillen?"},
    {"question_id": 87, "question_content": "Kun je je favoriete kinderactiviteit beschrijven?"},
    {"question_id": 88, "question_content": "Wat doe je meestal als je blij bent?"},
    {"question_id": 89, "question_content": "Wat vind je van muziek?"},
    {"question_id": 90, "question_content": "Wat is je favoriete manier om buiten tijd door te brengen?"},
    {"question_id": 91, "question_content": "Wat vind je van het belang van geschiedenis?"},
    {"question_id": 92, "question_content": "Wat is je favoriete manier om speciale gelegenheden te vieren?"},
    {"question_id": 93, "question_content": "Hoe ontspan je na een drukke dag?"},
    {"question_id": 94, "question_content": "Wat is je favoriete manier om nieuwe dingen te leren?"},
    {"question_id": 95, "question_content": "Wat vind je van kunst?"},
    {"question_id": 96, "question_content": "Wat is je favoriete filmgenre?"},
    {"question_id": 97, "question_content": "Kun je een moment beschrijven waarop je trots op jezelf was?"},
    {"question_id": 98, "question_content": "Wat vind je van vrijwilligerswerk?"},
    {"question_id": 99, "question_content": "Wat is je favoriete manier om een regenachtige dag door te brengen?"},
    {"question_id": 100, "question_content": "Wat vind je van het belang van vriendschap?"}
]